MANIFEST.in
README.rst
README.txt
setup.cfg
setup.py
docs/CREDITS.txt
docs/HISTORY.txt
docs/INSTALL.txt
docs/LICENSE.GPL
docs/LICENSE.txt
src/openmultimedia/__init__.py
src/openmultimedia.imagewatchdog.egg-info/PKG-INFO
src/openmultimedia.imagewatchdog.egg-info/SOURCES.txt
src/openmultimedia.imagewatchdog.egg-info/dependency_links.txt
src/openmultimedia.imagewatchdog.egg-info/entry_points.txt
src/openmultimedia.imagewatchdog.egg-info/namespace_packages.txt
src/openmultimedia.imagewatchdog.egg-info/not-zip-safe
src/openmultimedia.imagewatchdog.egg-info/requires.txt
src/openmultimedia.imagewatchdog.egg-info/top_level.txt
src/openmultimedia/imagewatchdog/__init__.py
src/openmultimedia/imagewatchdog/configlet.py
src/openmultimedia/imagewatchdog/configure.zcml
src/openmultimedia/imagewatchdog/interfaces.py
src/openmultimedia/imagewatchdog/migration.py
src/openmultimedia/imagewatchdog/subscribers.py
src/openmultimedia/imagewatchdog/testing.py
src/openmultimedia/imagewatchdog/profiles/default/controlpanel.xml
src/openmultimedia/imagewatchdog/profiles/default/metadata.xml
src/openmultimedia/imagewatchdog/profiles/default/registry.xml
src/openmultimedia/imagewatchdog/profiles/testing/metadata.xml
src/openmultimedia/imagewatchdog/script/install_and_migrate.py
src/openmultimedia/imagewatchdog/tests/__init__.py
src/openmultimedia/imagewatchdog/tests/test_configlet.py
src/openmultimedia/imagewatchdog/tests/test_convert.py
src/openmultimedia/imagewatchdog/tests/test_installation.py
src/openmultimedia/imagewatchdog/tests/test_migration.py