Metadata-Version: 1.1
Name: openmultimedia.imagewatchdog
Version: 1.0b1
Summary: A package to convert every image stored and uploaded to a Plone site to PNG format.
Home-page: https://github.com/OpenMultimedia/openmultimedia.imagewatchdog
Author: Juan Pablo Giménez
Author-email: jpg@rosario.com
License: GPLv2
Keywords: plone images jpeg gif png
Platform: UNKNOWN
Classifier: Development Status :: 4 - Beta
Classifier: Environment :: Web Environment
Classifier: Framework :: Plone
Classifier: Framework :: Plone :: 4.1
Classifier: Framework :: Plone :: 4.2
Classifier: Framework :: Plone :: 4.3
Classifier: Intended Audience :: System Administrators
Classifier: License :: OSI Approved :: GNU General Public License v2 (GPLv2)
Classifier: Operating System :: OS Independent
Classifier: Programming Language :: Python
Classifier: Programming Language :: Python :: 2.6
Classifier: Programming Language :: Python :: 2.7
Classifier: Topic :: Software Development :: Libraries :: Python Modules
